{
  "items": [
    {
      "text": "🔍 *ENRICH REVIEW*  \\[✨ ENRICHED\\]\n\n*Name:* Nenagh Castle\n*Country:* ireland\n*Region:* the heartlands\n*County:* County Tipperary\n*Type:* castle\n*Period:* 13th century\n*Coords:* 52.8632, -8.1995\n*Wikipedia:* https://en.wikipedia.org/wiki/Nenagh_Castle\n*Maps:* https://www.google.com/maps/search/Nenagh%20Castle/@52.8619,-8.1964,15z\n*Main Image:* https://upload.wikimedia.org/wikipedia/commons/thumb/7/72/Centre_of_Nenagh_-_panoramio.jpg/330px-Centre_of_Nenagh_-_panoramio.jpg\n*Gallery:* 8 images\n*Image Source:* wikipedia\n*Has Wikipedia:* yes\n*Has Google Places:* unknown\n\n*Description:*\nNenagh is the county town of County Tipperary in Ireland. Nenagh used to be a market town, and the site of the East Munster Ormond Fair.\n\n_Listing 1 of 260_",
      "listing": {
        "name": "Nenagh Castle",
        "country": "ireland",
        "region": "the-heartlands",
        "county": "County Tipperary",
        "lat": 52.8632,
        "lng": -8.1995,
        "mapsLink": "https://www.google.com/maps/search/Nenagh%20Castle/@52.8619,-8.1964,15z",
        "image": "https://upload.wikimedia.org/wikipedia/commons/thumb/7/72/Centre_of_Nenagh_-_panoramio.jpg/330px-Centre_of_Nenagh_-_panoramio.jpg",
        "imgSource": "wikipedia",
        "gallery": [
          "https://img.castlecore.uk/nenagh-castle-2.jpg",
          "https://img.castlecore.uk/nenagh-castle-3.jpg",
          "https://img.castlecore.uk/nenagh-castle-4.jpg",
          "https://img.castlecore.uk/nenagh-castle-5.jpg",
          "https://img.castlecore.uk/nenagh-castle-main-2.jpg",
          "https://img.castlecore.uk/nenagh-castle-main-3.jpg",
          "https://img.castlecore.uk/nenagh-castle-main-4.jpg",
          "https://img.castlecore.uk/nenagh-castle-main-5.jpg"
        ],
        "desc": "Nenagh is the county town of County Tipperary in Ireland. Nenagh used to be a market town, and the site of the East Munster Ormond Fair.",
        "type": "castle",
        "period": "13th century",
        "rating": 3.9,
        "tags": [
          "dramatic-ruin",
          "hidden-gem",
          "free"
        ],
        "source": "",
        "wiki": "https://en.wikipedia.org/wiki/Nenagh",
        "wikiImage": "https://upload.wikimedia.org/wikipedia/commons/thumb/7/72/Centre_of_Nenagh_-_panoramio.jpg/330px-Centre_of_Nenagh_-_panoramio.jpg",
        "reviewStatus": "flagged",
        "exists": "unverified",
        "hasWikipedia": "yes",
        "hasGooglePlaces": "unknown",
        "wikipediaUrl": "https://en.wikipedia.org/wiki/Nenagh_Castle",
        "needsEnrich": true,
        "enrichReviewQueued": true,
        "enrichStatus": "enriched",
        "enrichReviewDate": "2026-05-17",
        "enrichNotes": ""
      },
      "ts": 1779060605243
    },
    {
      "text": "🔍 *ENRICH REVIEW*  \\[🔧 STILL IN PROGRESS\\]\n\n*Name:* Layde Church\n*Country:* ireland\n*Region:* ulster and the north\n*County:* County Antrim\n*Type:* abbey\n*Period:* 13th century\n*Coords:* 55.205, -6.035\n*Wikipedia:* https://en.wikipedia.org/wiki/Late_church_cantatas_by_Johann_Sebastian_Bach\n*Maps:* https://www.google.com/maps/search/Layde%20Church/@55.205,-6.035,15z\n*Main Image:* https://img.castlecore.uk/layde-church.jpg\n*Gallery:* 4 images\n*Image Source:* CDN\n*Has Wikipedia:* no\n*Has Google Places:* unknown\n*Enrich Notes:* no wikipedia page. \n\n*Description:*\nThe late church cantatas by Johann Sebastian Bach are sacred cantatas he composed after his fourth cycle of 1728–29. Whether Bach still composed a full cantata cycle in the last 20 years of his life is not known, but the extant cantatas of this period written for occasions of the liturgical year are sometimes referred to as his fifth cycle, as, according to his obituary, he would have written five such cycles – inasmuch as such cantatas were not late additions to earlier cycles, or were adopted in his oratorios.\n\n_Listing 2 of 260_",
      "listing": {
        "name": "Layde Church",
        "country": "ireland",
        "region": "ulster-and-the-north",
        "county": "County Antrim",
        "lat": 55.205,
        "lng": -6.035,
        "mapsLink": "https://www.google.com/maps/search/Layde%20Church/@55.205,-6.035,15z",
        "image": "https://img.castlecore.uk/layde-church.jpg",
        "imgSource": "CDN",
        "gallery": [
          "https://img.castlecore.uk/layde-church-2.jpg",
          "https://img.castlecore.uk/layde-church-3.jpg",
          "https://img.castlecore.uk/layde-church-4.jpg",
          "https://img.castlecore.uk/layde-church-5.jpg"
        ],
        "desc": "The late church cantatas by Johann Sebastian Bach are sacred cantatas he composed after his fourth cycle of 1728–29. Whether Bach still composed a full cantata cycle in the last 20 years of his life is not known, but the extant cantatas of this period written for occasions of the liturgical year are sometimes referred to as his fifth cycle, as, according to his obituary, he would have written five such cycles – inasmuch as such cantatas were not late additions to earlier cycles, or were adopted in his oratorios.",
        "type": "abbey",
        "period": "13th century",
        "rating": 3.9,
        "tags": [
          "coastal",
          "ruins-romantic",
          "medieval",
          "atmospheric",
          "photogenic",
          "free-entry"
        ],
        "source": [
          {
            "name": "Antrim Heritage",
            "url": "https://www.visitcausewaycoastandglens.com/"
          },
          {
            "name": "Heritage Ireland",
            "url": "https://heritageireland.ie/"
          }
        ],
        "wiki": "https://en.wikipedia.org/wiki/Late_church_cantatas_by_Johann_Sebastian_Bach",
        "reviewStatus": "flagged",
        "exists": "unverified",
        "hasWikipedia": "no",
        "hasGooglePlaces": "unknown",
        "needsEnrich": true,
        "enrichReviewQueued": true,
        "enrichStatus": "in-progress",
        "enrichReviewDate": "2026-05-17",
        "enrichNote": "no wikipedia page. ",
        "enrichNotes": "no wikipedia page. "
      },
      "ts": 1779060674297
    }
  ]
}