{
  "items": [
    {
      "text": "🔍 *ENRICH REVIEW*  \\[✨ ENRICHED\\]\n\n*Name:* Lytes Cary Manor\n*Country:* england\n*Region:* south west\n*County:* Somerset\n*Type:* castle\n*Period:* 14th-16th century\n*Coords:* 51.0358, -2.6677\n*Wikipedia:* https://en.wikipedia.org/wiki/Lytes_Cary\n*Maps:* https://www.google.com/maps/search/Lytes%20Cary%20Manor/@51.0217,-2.6917,15z\n*Main Image:* https://lh3.googleusercontent.com/place-photos/AJRVUZNUg5PfgpyaHu7Wh6bDG_Id-oJxjFYITOsIBpwN16lnRBjnQiQARTfAOcnc0eS3gS00MXrMaV3c1083WfqH7XBLQVrdYgeapNqJCyHSADa7we6uh5Ry4lf9875Jw3vYjlFN-Led8TNqZ6ODWA=s4800-w1200\n*Gallery:* 0 images\n*Image Source:* google\n*Has Wikipedia:* unknown\n*Has Google Places:* unknown\n\n*Description:*\nLytes Cary is a manor house with associated chapel and gardens near Charlton Mackrell and Somerton in Somerset, England. The property, owned by the National Trust, has parts dating to the 14th century, with other sections dating to the 15th, 16th, 18th, and 20th centuries. \"Yet all parts blend to perfection with one another and with the gentle sunny landscape that surrounds them,\" comments Nikolaus Pevsner. The House is listed as Grade I by English Heritage.\n\n_Listing 1 of 28_",
      "listing": {
        "name": "Lytes Cary Manor",
        "country": "england",
        "region": "south-west",
        "county": "Somerset",
        "lat": 51.0358,
        "lng": -2.6677,
        "mapsLink": "https://www.google.com/maps/search/Lytes%20Cary%20Manor/@51.0217,-2.6917,15z",
        "image": "https://lh3.googleusercontent.com/place-photos/AJRVUZNUg5PfgpyaHu7Wh6bDG_Id-oJxjFYITOsIBpwN16lnRBjnQiQARTfAOcnc0eS3gS00MXrMaV3c1083WfqH7XBLQVrdYgeapNqJCyHSADa7we6uh5Ry4lf9875Jw3vYjlFN-Led8TNqZ6ODWA=s4800-w1200",
        "imgSource": "google",
        "gallery": [],
        "desc": "Lytes Cary is a manor house with associated chapel and gardens near Charlton Mackrell and Somerton in Somerset, England. The property, owned by the National Trust, has parts dating to the 14th century, with other sections dating to the 15th, 16th, 18th, and 20th centuries. \"Yet all parts blend to perfection with one another and with the gentle sunny landscape that surrounds them,\" comments Nikolaus Pevsner. The House is listed as Grade I by English Heritage.",
        "type": "castle",
        "period": "14th-16th century",
        "rating": 4.3,
        "tags": [
          "medieval",
          "gardens",
          "atmospheric",
          "tearoom-cafe"
        ],
        "source": [
          {
            "name": "National Trust",
            "url": "https://www.nationaltrust.org.uk/visit/somerset/lytes-cary-manor"
          }
        ],
        "wiki": "https://en.wikipedia.org/wiki/Lytes_Cary",
        "wikiImage": "https://upload.wikimedia.org/wikipedia/commons/thumb/5/58/Lytes_Cary_1920x1200.jpg/330px-Lytes_Cary_1920x1200.jpg",
        "reviewStatus": "flagged",
        "imageAttribution": {
          "artist": "Wehha",
          "license": "CC BY-SA 3.0",
          "description": "Lytes Cary in Somerset.  National Trust Property",
          "credit": "Own work",
          "source": "Wikimedia Commons"
        },
        "mainImageSource": "google",
        "imageReviewDone": true,
        "needsEnrich": true,
        "status": "flagged",
        "enrichStatus": "enriched",
        "enrichReviewDate": "2026-05-17",
        "enrichNotes": ""
      },
      "ts": 1779045758836
    },
    {
      "text": "🔍 *ENRICH REVIEW*  \\[✨ ENRICHED\\]\n\n*Name:* Clevedon Court\n*Country:* england\n*Region:* south west\n*County:* Somerset\n*Type:* castle\n*Period:* 14th century\n*Coords:* 51.4402, -2.8321\n*Wikipedia:* https://en.wikipedia.org/wiki/Clevedon_Court\n*Maps:* https://www.google.com/maps/search/Clevedon%20Court/@51.4383,-2.8717,15z\n*Main Image:* https://lh3.googleusercontent.com/places/ANXAkqEJEmuvqxEqX1o70F62B3nUvOpc-q3_GzD5YG4LoIjNZHWhjnqTe5bIXolTfpYXAERSP6uDO-jbLxjpPgwwQFRsyTmF43qwvA=s4800-w747\n*Gallery:* 0 images\n*Image Source:* google\n*Has Wikipedia:* unknown\n*Has Google Places:* unknown\n\n*Description:*\nClevedon Court is a manor house on Court Hill in Clevedon, North Somerset, England, dating from the early 14th century. It is owned by the National Trust and is designated as a Grade I listed building.\n\n_Listing 2 of 28_",
      "listing": {
        "name": "Clevedon Court",
        "country": "england",
        "region": "south-west",
        "county": "Somerset",
        "lat": 51.4402,
        "lng": -2.8321,
        "mapsLink": "https://www.google.com/maps/search/Clevedon%20Court/@51.4383,-2.8717,15z",
        "image": "https://lh3.googleusercontent.com/places/ANXAkqEJEmuvqxEqX1o70F62B3nUvOpc-q3_GzD5YG4LoIjNZHWhjnqTe5bIXolTfpYXAERSP6uDO-jbLxjpPgwwQFRsyTmF43qwvA=s4800-w747",
        "imgSource": "google",
        "gallery": [],
        "desc": "Clevedon Court is a manor house on Court Hill in Clevedon, North Somerset, England, dating from the early 14th century. It is owned by the National Trust and is designated as a Grade I listed building.",
        "type": "castle",
        "period": "14th century",
        "rating": 4.3,
        "tags": [
          "well-preserved",
          "atmospheric",
          "gardens",
          "medieval",
          "tearoom-cafe",
          "guided-tours"
        ],
        "source": [
          {
            "name": "National Trust",
            "url": "https://www.nationaltrust.org.uk/visit/bath-bristol/clevedon-court"
          },
          {
            "name": "Wikipedia",
            "url": "https://en.wikipedia.org/wiki/Clevedon_Court"
          }
        ],
        "wiki": "https://en.wikipedia.org/wiki/Clevedon_Court",
        "wikiImage": "https://upload.wikimedia.org/wikipedia/commons/thumb/9/92/Clevedon_2_%28front%2C_2011%29.jpg/330px-Clevedon_2_%28front%2C_2011%29.jpg",
        "reviewStatus": "flagged",
        "imageAttribution": {
          "artist": "Arthur266",
          "license": "CC BY-SA 3.0",
          "description": "Clevedon Court",
          "credit": "Own work",
          "source": "Wikimedia Commons"
        },
        "mainImageSource": "google",
        "imageReviewDone": true,
        "needsEnrich": true,
        "status": "flagged",
        "enrichStatus": "enriched",
        "enrichReviewDate": "2026-05-17",
        "enrichNotes": ""
      },
      "ts": 1779045773727
    },
    {
      "text": "🔍 *ENRICH REVIEW*  \\[✨ ENRICHED\\]\n\n*Name:* A La Ronde\n*Country:* england\n*Region:* south west\n*County:* Devon\n*Type:* castle\n*Period:* 18th century\n*Coords:* 50.6417, -3.4088\n*Wikipedia:* https://en.wikipedia.org/wiki/A_la_Ronde\n*Maps:* https://www.google.com/maps/search/A%20La%20Ronde/@50.64,-3.4017,15z\n*Main Image:* https://lh3.googleusercontent.com/place-photos/AJRVUZMyZwB9f_3b9OZtUcqlyGiIDmkC4kMq_Dp0zGXb4YucUDsZIJsVstRwH2VmEtEsAuW_UV8sDG1vqsvPX4fr-aIxXS0IPwT3pM2Sbuw_5wo9K945TV-8TvVU1lnAzqGGondFqWGOoVKuOBfKkUeot5r8Ug=s4800-w1200\n*Gallery:* 0 images\n*Image Source:* google\n*Has Wikipedia:* unknown\n*Has Google Places:* unknown\n\n*Description:*\nA la Ronde is an 18th-century, 16-sided cottage orné near Lympstone, Exmouth, Devon, England, in the ownership of the National Trust. The house was built for two spinster cousins, Jane and Mary Parminter. It is a Grade I listed building, as are the adjacent Point-In-View chapel, school and almshouses, together with a manse, which were also built by the cousins. The gardens are Grade II listed in the National Register of Historic Parks and Gardens.\n\n_Listing 3 of 28_",
      "listing": {
        "name": "A La Ronde",
        "country": "england",
        "region": "south-west",
        "county": "Devon",
        "lat": 50.6417,
        "lng": -3.4088,
        "mapsLink": "https://www.google.com/maps/search/A%20La%20Ronde/@50.64,-3.4017,15z",
        "image": "https://lh3.googleusercontent.com/place-photos/AJRVUZMyZwB9f_3b9OZtUcqlyGiIDmkC4kMq_Dp0zGXb4YucUDsZIJsVstRwH2VmEtEsAuW_UV8sDG1vqsvPX4fr-aIxXS0IPwT3pM2Sbuw_5wo9K945TV-8TvVU1lnAzqGGondFqWGOoVKuOBfKkUeot5r8Ug=s4800-w1200",
        "imgSource": "google",
        "gallery": [],
        "desc": "A la Ronde is an 18th-century, 16-sided cottage orné near Lympstone, Exmouth, Devon, England, in the ownership of the National Trust. The house was built for two spinster cousins, Jane and Mary Parminter. It is a Grade I listed building, as are the adjacent Point-In-View chapel, school and almshouses, together with a manse, which were also built by the cousins. The gardens are Grade II listed in the National Register of Historic Parks and Gardens.",
        "type": "castle",
        "period": "18th century",
        "rating": 4.3,
        "tags": [
          "photogenic",
          "atmospheric",
          "gardens",
          "tearoom-cafe",
          "gift-shop",
          "kid-friendly"
        ],
        "source": [
          {
            "name": "National Trust",
            "url": "https://www.nationaltrust.org.uk/visit/devon/a-la-ronde"
          },
          {
            "name": "Wikipedia",
            "url": "https://en.wikipedia.org/wiki/A_la_Ronde"
          },
          {
            "name": "National Trust Collections",
            "url": "https://www.nationaltrustcollections.org.uk/place/a-la-ronde"
          }
        ],
        "wiki": "https://en.wikipedia.org/wiki/A_la_Ronde",
        "wikiImage": "https://upload.wikimedia.org/wikipedia/commons/thumb/c/c1/A_La_Ronde_%285523285615%29.jpg/330px-A_La_Ronde_%285523285615%29.jpg",
        "reviewStatus": "flagged",
        "imageAttribution": {
          "artist": "Becks",
          "license": "CC BY 2.0",
          "description": "A La Ronde",
          "credit": "A La Ronde",
          "source": "Wikimedia Commons"
        },
        "mainImageSource": "google",
        "imageReviewDone": true,
        "needsEnrich": true,
        "status": "flagged",
        "enrichStatus": "enriched",
        "enrichReviewDate": "2026-05-17",
        "enrichNotes": ""
      },
      "ts": 1779045785685
    },
    {
      "text": "🔍 *ENRICH REVIEW*  \\[✨ ENRICHED\\]\n\n*Name:* Tattershall Castle\n*Country:* england\n*Region:* the midlands\n*County:* Lincolnshire\n*Type:* tower house\n*Period:* 15th century\n*Coords:* 53.10133333, -0.19261111\n*Wikipedia:* https://en.wikipedia.org/wiki/Tattershall_Castle%2C_Lincolnshire\n*Maps:* https://www.google.com/maps/search/Tattershall%20Castle/@53.1084,-0.2101,15z\n*Main Image:* https://lh3.googleusercontent.com/place-photos/AJRVUZMRU7r-ZbEj9gQaFs7eip5qHt9XFJ8JU9JUrnGq8SDWR8ZyvxdEU0WO5-qla02q0sDbdqbSb3g5fczJfEhcn3J_FbfuyF0PiuKSaURubFJq3kYLweXX9e0Aqnzm6rrH0yr31R3lNA_2H3-Yjq0=s4800-w1200\n*Gallery:* 0 images\n*Image Source:* google\n*Has Wikipedia:* unknown\n*Has Google Places:* unknown\n*Enrich Notes:* update google places link - https://maps.app.goo.gl/yw271Qv6ak6sxbGRA\n\n*Description:*\nTattershall Castle is a castle in Tattershall, Lincolnshire, England. Since 1925 it has been in the care of the National Trust.\n\n_Listing 4 of 28_",
      "listing": {
        "name": "Tattershall Castle",
        "country": "england",
        "region": "the-midlands",
        "county": "Lincolnshire",
        "lat": 53.10133333,
        "lng": -0.19261111,
        "mapsLink": "https://www.google.com/maps/search/Tattershall%20Castle/@53.1084,-0.2101,15z",
        "image": "https://lh3.googleusercontent.com/place-photos/AJRVUZMRU7r-ZbEj9gQaFs7eip5qHt9XFJ8JU9JUrnGq8SDWR8ZyvxdEU0WO5-qla02q0sDbdqbSb3g5fczJfEhcn3J_FbfuyF0PiuKSaURubFJq3kYLweXX9e0Aqnzm6rrH0yr31R3lNA_2H3-Yjq0=s4800-w1200",
        "imgSource": "google",
        "gallery": [],
        "desc": "Tattershall Castle is a castle in Tattershall, Lincolnshire, England. Since 1925 it has been in the care of the National Trust.",
        "type": "tower house",
        "period": "15th century",
        "rating": 4.3,
        "tags": [
          "dramatic-ruin",
          "hidden-gem",
          "photogenic"
        ],
        "source": "",
        "wiki": "https://en.wikipedia.org/wiki/Tattershall_Castle%2C_Lincolnshire",
        "wikiImage": "https://upload.wikimedia.org/wikipedia/commons/thumb/b/b9/Tattershall_Castle%2C_2006.jpg/330px-Tattershall_Castle%2C_2006.jpg",
        "reviewStatus": "flagged",
        "imageAttribution": {
          "artist": "Brian from UK",
          "license": "CC BY-SA 2.0",
          "description": "Tattershall Castle is one of a complex of buildings built by Ralph, Lord Cromwell, in the late 15th century and which also included Tattershall College, the collegiate church and the Almshouse.",
          "credit": "Tattershall Castle, Tatterhsall, Lincolnshire",
          "source": "Wikimedia Commons"
        },
        "mainImageSource": "google",
        "imageReviewDone": true,
        "needsEnrich": true,
        "status": "flagged",
        "enrichStatus": "enriched",
        "enrichReviewDate": "2026-05-17",
        "enrichNote": "update google places link - https://maps.app.goo.gl/yw271Qv6ak6sxbGRA",
        "enrichNotes": "update google places link - https://maps.app.goo.gl/yw271Qv6ak6sxbGRA"
      },
      "ts": 1779045808130
    }
  ]
}